main.py
.cursor/rules/control.md
.cursor/rules/android/amdroid-common.mdc
.cursor/rules/android/amdroid-ffmpeg.mdc
.cursor/rules/android/amdroid-ijkplayer.mdc
.cursor/rules/android/amdroid-webrtc.mdc
.cursor/rules/back/go.mdc
.cursor/rules/back/java-common.mdc
.cursor/rules/front/front-react.mdc
.cursor/rules/front/front-vue.mdc
.cursor/rules/product/product.mdc
.cursor/rules/product/yunying.mdc
.cursor/rules/rules-modules/code-implementation.md
.cursor/rules/rules-modules/expert-selector.md
.cursor/rules/rules-modules/product-analyst.md
.cursor/rules/rules-modules/quality-assurance.md
.cursor/rules/rules-modules/tech-architect.md
.cursor/rules/rules-modules/workflow-controller.md
.cursor/rules/web3/solana.mdc
.cursor/rules/web3/solidity.mdc
.cursor/rules/web3/web3-common.mdc
.cursor/rules/web3/web3-go.mdc
iacc_mcp_server-2.0.2.dist-info/METADATA
iacc_mcp_server-2.0.2.dist-info/WHEEL
iacc_mcp_server-2.0.2.dist-info/entry_points.txt
iacc_mcp_server-2.0.2.dist-info/licenses/LICENSE
iacc_mcp_server-2.0.2.dist-info/RECORD
